bfgcardplay/__init__.py
bfgcardplay/_version.py
bfgcardplay/card_player_components.py
bfgcardplay/cards.py
bfgcardplay/dashboard.py
bfgcardplay/data_classes.py
bfgcardplay/declarer_play.py
bfgcardplay/defender_play.py
bfgcardplay/first_seat.py
bfgcardplay/first_seat_declarer.py
bfgcardplay/first_seat_declarer_nt.py
bfgcardplay/first_seat_declarer_suit.py
bfgcardplay/first_seat_defender.py
bfgcardplay/fourth_seat.py
bfgcardplay/fourth_seat_declarer.py
bfgcardplay/fourth_seat_defender.py
bfgcardplay/global_variables.py
bfgcardplay/logger.py
bfgcardplay/manager.py
bfgcardplay/opening_lead.py
bfgcardplay/opening_lead_card.py
bfgcardplay/opening_lead_suit.py
bfgcardplay/player.py
bfgcardplay/second_seat.py
bfgcardplay/second_seat_declarer.py
bfgcardplay/second_seat_defender.py
bfgcardplay/suggested_card.py
bfgcardplay/third_seat.py
bfgcardplay/third_seat_declarer.py
bfgcardplay/third_seat_defender.py
bfgcardplay/utilities.py
bfgcardplay-1.2.8.dist-info/METADATA
bfgcardplay-1.2.8.dist-info/WHEEL
bfgcardplay-1.2.8.dist-info/RECORD
