Metadata-Version: 2.4
Name: bfgcardplay
Version: 1.2.8
Summary: Cardplay for BfG
Author: Jeff
Author-email: jeffwatkins2000@gmail.com
Requires-Python: >=3.10
Classifier: Programming Language :: Python :: 3
Classifier: Programming Language :: Python :: 3.10
Classifier: Programming Language :: Python :: 3.11
Classifier: Programming Language :: Python :: 3.12
Classifier: Programming Language :: Python :: 3.13
Classifier: Programming Language :: Python :: 3.14
